pibooth_picamera2.py
pibooth_picamera2-1.0.2.dist-info/LICENSE
pibooth_picamera2-1.0.2.dist-info/METADATA
pibooth_picamera2-1.0.2.dist-info/WHEEL
pibooth_picamera2-1.0.2.dist-info/entry_points.txt
pibooth_picamera2-1.0.2.dist-info/top_level.txt
pibooth_picamera2-1.0.2.dist-info/RECORD
