Metadata-Version: 2.1
Name: pibooth-picamera2
Version: 1.0.2
Home-page: https://github.com/Smatnemo/pibooth-picamera2
Download-URL: https://github.com/Smatnemo/pibooth-picamera2/archive/1.0.2.tar.gz
Author: Tertese Moses
License: GPLv3
Keywords: Raspberry Pi,camera,photobooth,picamera2
Platform: unix
Platform: linux
Classifier: Development Status :: 5 - Production/Stable
Classifier: Environment :: Other Environment
Classifier: Intended Audience :: Developers
Classifier: Intended Audience :: End Users/Desktop
Classifier: License :: OSI Approved :: GNU General Public License v3 or later (GPLv3+)
Classifier: Operating System :: POSIX :: Linux
Classifier: Programming Language :: Python :: 3.9
Classifier: Natural Language :: English
Classifier: Topic :: Multimedia :: Graphics :: Capture :: Digital Camera
Requires-Python: >=3.9
License-File: LICENSE
Requires-Dist: pibooth (>=2.0.0)
